proxmoxer_mcp_server/__init__.py
proxmoxer_mcp_server-0.1.0.dist-info/licenses/LICENSE
proxmoxer_mcp_server-0.1.0.dist-info/METADATA
proxmoxer_mcp_server-0.1.0.dist-info/WHEEL
proxmoxer_mcp_server-0.1.0.dist-info/entry_points.txt
proxmoxer_mcp_server-0.1.0.dist-info/top_level.txt
proxmoxer_mcp_server-0.1.0.dist-info/RECORD
