Metadata-Version: 2.4
Name: proxmoxer-mcp-server
Version: 0.1.0
Summary: Proxmox VE MCP Server - Manages Proxmox infrastructure via MCP protocol
Author-email: "Justin \"'Airstrike' Ivanov\" Sacco" <airstrikeivanov@airstrikeivanov.com>
Maintainer-email: "Justin \"'Airstrike' Ivanov\" Sacco" <airstrikeivanov@airstrikeivanov.com>
License-Expression: MIT
Project-URL: Homepage, https://git.airstrikeivanov.com/airstrikeivanov/proxmoxer-mcp-server
Project-URL: Repository, https://git.airstrikeivanov.com/airstrikeivanov/proxmoxer-mcp-server
Project-URL: Issues, https://git.airstrikeivanov.com/airstrikeivanov/proxmoxer-mcp-server/issues
Keywords: proxmox,mcp,virtualization,infrastructure,homelab
Classifier: Development Status :: 4 - Beta
Classifier: Intended Audience :: Developers
Classifier: Intended Audience :: System Administrators
Classifier: Operating System :: OS Independent
Classifier: Programming Language :: Python :: 3
Classifier: Programming Language :: Python :: 3.10
Classifier: Programming Language :: Python :: 3.11
Classifier: Programming Language :: Python :: 3.12
Classifier: Topic :: System :: Systems Administration
Classifier: Topic :: Software Development :: Libraries :: Python Modules
Requires-Python: >=3.10
License-File: LICENSE
Requires-Dist: fastmcp>=2.14.4
Requires-Dist: proxmoxer>=2.2.0
Provides-Extra: dev
Requires-Dist: pytest>=7.0.0; extra == "dev"
Requires-Dist: pytest-cov>=4.0.0; extra == "dev"
Requires-Dist: black>=23.0.0; extra == "dev"
Requires-Dist: ruff>=0.1.0; extra == "dev"
Requires-Dist: mypy>=1.0.0; extra == "dev"
Requires-Dist: types-requests; extra == "dev"
Provides-Extra: test
Requires-Dist: pytest>=7.0.0; extra == "test"
Requires-Dist: pytest-cov>=4.0.0; extra == "test"
Requires-Dist: pytest-asyncio>=0.21.0; extra == "test"
Dynamic: license-file
